EC_CMD_Wallet/__init__.py
EC_CMD_Wallet/const.py
EC_CMD_Wallet/scripts.py
EC_CMD_Wallet/balance/__init__.py
EC_CMD_Wallet/balance/_btc.py
EC_CMD_Wallet/balance/_eth.py
EC_CMD_Wallet/balance/methods.py
EC_CMD_Wallet/config/__init__.py
EC_CMD_Wallet/config/default.py
EC_CMD_Wallet/config/utils.py
EC_CMD_Wallet/config/verify.py
EC_CMD_Wallet/new/__init__.py
EC_CMD_Wallet/new/_btc.py
EC_CMD_Wallet/new/_eth.py
EC_CMD_Wallet/new/methods.py
EC_CMD_Wallet/send/__init__.py
EC_CMD_Wallet/send/_btc.py
EC_CMD_Wallet/send/_eth.py
EC_CMD_Wallet/send/methods.py
EC_CMD_Wallet-0.0.1.dist-info/DESCRIPTION.rst
EC_CMD_Wallet-0.0.1.dist-info/METADATA
EC_CMD_Wallet-0.0.1.dist-info/RECORD
EC_CMD_Wallet-0.0.1.dist-info/WHEEL
EC_CMD_Wallet-0.0.1.dist-info/entry_points.txt
EC_CMD_Wallet-0.0.1.dist-info/metadata.json
EC_CMD_Wallet-0.0.1.dist-info/top_level.txt
