Metadata-Version: 2.0
Name: EC-CMD-Wallet
Version: 0.0.1
Summary: simple tools
Home-page: UNKNOWN
Author: huangsizhe
Author-email: UNKNOWN
License: MIT
Keywords: tools
Platform: UNKNOWN
Classifier: Development Status :: 3 - Alpha
Classifier: Intended Audience :: Developers
Classifier: License :: OSI Approved :: MIT License
Classifier: Programming Language :: Python :: 3.5
Classifier: Programming Language :: Python :: 3.6
Classifier: Topic :: Documentation :: Sphinx
Requires-Dist: autopep8 (==1.4.3)
Requires-Dist: coverage (==4.5.2)
Requires-Dist: lxml (==4.2.5)
Requires-Dist: mypy (==0.641)
Requires-Dist: mypy-extensions (==0.4.1)
Requires-Dist: pep8 (==1.7.1)
Requires-Dist: pycodestyle (==2.4.0)
Requires-Dist: pydocstyle (==3.0.0)
Requires-Dist: six (==1.11.0)
Requires-Dist: snowballstemmer (==1.2.1)
Requires-Dist: typed-ast (==1.1.0)
Requires-Dist: voluptuous (==0.11.5)
